Sistemas Digitais 2/Aula 3/fpa.v
module rom_8 (
    input [2:0] addr , 
    input OE, 
    output reg [31:0] out 
); 
    reg [31:0] data [7:0]; 
    initial begin 
        data [0] = 32'h0986ab68; 
        data [1] = 32'h10385ba9; 
        data [2] = 32'h3F800000; 
        data [3] = 32'h3C449BA6; 
        data [4] = 32'h40400000;
        data [5] = 32'h41200000; 
        data [6] = 32'h3EA00000;
        data [7] = 32'h3F600000; 
    end 
    always @(addr, OE) 
        if (OE == 1'b1) 
            out = data[addr]; 
        else 
            out = 32'bz;
endmodule


module ram_4 (
    input [31:0] in,
    input [1:0] addr,
    input RW, OE,
    output reg [31:0] out
);
    reg [31:0] data [3:0];
    always @(in, addr, RW, OE) begin
        if (RW == 1'b0 & OE == 1'b1)
            out = data[addr];
        else
            out = 32'bz;
        if (RW == 1'b1)
            data[addr] = in;
    end
endmodule

module fpa(
    input [1:0] ram_addr,  
    output [31:0] ram_out,
    output reg done
);
    reg clk;
    initial clk = 0;
    always #5 clk = ~clk; 

    reg [2:0] rom_addr;
    reg [1:0] addr_counter;
    reg rom_OE;
    reg ram_RW;
    reg ram_OE;
    reg adder_en;
    reg [31:0] operand_1;
    reg [31:0] operand_2;
    wire [31:0] rom_out;
    wire [31:0] adder_sum;
    wire [1:0] ram_addr_mux;
    assign ram_addr_mux = (ram_RW ? addr_counter : ram_addr);

    rom_8 rom_inst (
        .addr(rom_addr),
        .OE(rom_OE),
        .out(rom_out)
    );

    ram_4 ram_inst (
        .in(adder_sum),
        .addr(ram_addr_mux),
        .RW(ram_RW),
        .OE(ram_OE),
        .out(ram_out)
    );

    adder fp_adder (
        .operand_1(operand_1),
        .operand_2(operand_2),
        .clk(clk),
        .en(adder_en),
        .sum(adder_sum)
    );

    reg [3:0] state;
    parameter IDLE             = 4'd0,
              READ_OP1_START   = 4'd1,
              READ_OP1_WAIT    = 4'd2,
              READ_OP2_START   = 4'd3,
              READ_OP2_WAIT    = 4'd4,
              COMPUTE_START    = 4'd5,
              COMPUTE_WAIT     = 4'd6,
              WRITE_RAM        = 4'd7,
              DONE_STATE       = 4'd8;

    initial begin
        state <= IDLE;
        rom_addr <= 3'd0;
        addr_counter <= 2'd0;
        rom_OE <= 1'b0;
        ram_RW <= 1'b0;
        ram_OE <= 1'b0;
        adder_en <= 1'b0;
        done <= 1'b0;
        operand_1 <= 32'd0;
        operand_2 <= 32'd0;
    end

    always @(posedge clk) begin
        case(state)
            IDLE: begin
                rom_addr <= 3'd0;
                addr_counter <= 2'd0;
                rom_OE <= 1'b1; 
                ram_RW <= 1'b0; 
                ram_OE <= 1'b0;
                adder_en <= 1'b0;
                done <= 1'b0;
                state <= READ_OP1_START;
            end

            READ_OP1_START: begin
                rom_addr <= {addr_counter, 1'b0};
                state <= READ_OP1_WAIT;
            end

            READ_OP1_WAIT: begin
                operand_1 <= rom_out;
                state <= READ_OP2_START;
            end

            READ_OP2_START: begin
                rom_addr <= {addr_counter, 1'b0} + 3'b001;
                state <= READ_OP2_WAIT;
            end

            READ_OP2_WAIT: begin
                operand_2 <= rom_out;
                state <= COMPUTE_START;
            end

            COMPUTE_START: begin
                adder_en <= 1'b1;
                state <= COMPUTE_WAIT;
            end

            COMPUTE_WAIT: begin
                adder_en <= 1'b0;
                state <= WRITE_RAM;
            end

            WRITE_RAM: begin
                ram_RW <= 1'b1; 
                ram_OE <= 1'b0; 
                if (addr_counter == 2'd3) begin
                    state <= DONE_STATE;
                end else begin
                    addr_counter <= addr_counter + 1;
                    state <= READ_OP1_START;
                end
            end

            DONE_STATE: begin
                ram_RW <= 1'b0;
                ram_OE <= 1'b1;
                done <= 1'b1;
                state <= DONE_STATE;
            end

            default: state <= IDLE;
        endcase
    end
endmodule

SD 2/Aula 3/fpa_tb.v
module adder(
    input [31:0] operand_1, operand_2,
    input clk, en,
    output reg [31:0] sum = 32'bz
);
    // IEEE 754 components extraction
    wire sign_a = operand_1[31];
    wire sign_b = operand_2[31];
    wire [7:0] exp_a = operand_1[30:23];
    wire [7:0] exp_b = operand_2[30:23];
    wire [22:0] frac_a = operand_1[22:0];
    wire [22:0] frac_b = operand_2[22:0];
    
    // Internal variables for calculation
    reg sign_result;
    reg [7:0] exp_result;
    reg [22:0] frac_result;
    reg [24:0] frac_a_extended, frac_b_extended;
    reg [24:0] frac_larger, frac_smaller;
    reg [24:0] aligned_smaller;
    reg [24:0] sum_fractions;
    reg [7:0] exp_larger;
    reg [7:0] shift_amount;
    
    // FP addition on enable signal
    always @(posedge clk) begin
        if (en) begin
            // Handle special cases
            if (exp_a == 0 && frac_a == 0) begin
                // If a is zero, result is b
                sum <= operand_2;
            end
            else if (exp_b == 0 && frac_b == 0) begin
                // If b is zero, result is a
                sum <= operand_1;
            end
            else begin
                // Normal case - simplified floating point addition
                
                // Step 1: Extend fractions with implicit bit and guard bit
                frac_a_extended = {|exp_a, frac_a, 1'b0};
                frac_b_extended = {|exp_b, frac_b, 1'b0};
                
                // Step 2: Determine which exponent is larger
                if (exp_a > exp_b) begin
                    exp_larger = exp_a;
                    frac_larger = frac_a_extended;
                    frac_smaller = frac_b_extended;
                    shift_amount = exp_a - exp_b;
                end
                else begin
                    exp_larger = exp_b;
                    frac_larger = frac_b_extended;
                    frac_smaller = frac_a_extended;
                    shift_amount = exp_b - exp_a;
                end
                
                // Step 3: Align fractions
                aligned_smaller = frac_smaller >> shift_amount;
                
                // Step 4: Add/subtract fractions based on signs
                if (sign_a == sign_b) begin
                    // Same sign: add fractions
                    sum_fractions = frac_larger + aligned_smaller;
                    sign_result = sign_a;
                end
                else begin
                    // Different signs: subtract smaller from larger
                    if (frac_larger >= aligned_smaller) begin
                        sum_fractions = frac_larger - aligned_smaller;
                        sign_result = (exp_a > exp_b) ? sign_a : sign_b;
                    end
                    else begin
                        sum_fractions = aligned_smaller - frac_larger;
                        sign_result = (exp_a > exp_b) ? ~sign_a : ~sign_b;
                    end
                end
                
                // Step 5: Normalize result
                exp_result = exp_larger;
                frac_result = sum_fractions[23:1]; // Extract the 23 bits of fraction
                
                // Handle overflow
                if (sum_fractions[24]) begin
                    frac_result = sum_fractions[24:2];
                    exp_result = exp_result + 1;
                end
                
                // Normalize for leading zeros (simplified)
                if (sum_fractions[23:1] == 0) begin
                    exp_result = 0; // Result is zero
                end
                
                // Combine sign, exponent and fraction
                sum = {sign_result, exp_result, frac_result};
            end
        end
    end
endmodule

module fpa_tb;
    // Outputs from DUT
    wire [31:0] ram_out;
    wire done;
    
    // Inputs to DUT
    reg [1:0] ram_addr;
    
    // Instantiate the DUT
    fpa dut (
        .ram_addr(ram_addr),
        .ram_out(ram_out),
        .done(done)
    );
    
    // Monitor signals
    initial begin
        $monitor("Time=%0t | State=%0d | rom_addr=%0d | ram_addr=%0d | op1=%h | op2=%h | sum=%h | done=%b",
                 $time, dut.state, dut.rom_addr, dut.ram_addr_mux, dut.operand_1, dut.operand_2, 
                 dut.adder_sum, done);
    end
    
    // Test sequence
    initial begin
        $dumpfile("fpa_tb.vcd");
        $dumpvars(0, fpa_tb);
        
        // Initialize inputs
        ram_addr = 2'b00;
        
        // Wait for the FPA to complete its operations
        wait(done);
        
        // Read values from RAM
        #10;
        ram_addr = 2'b00;
        #10;
        $display("RAM[0] = %h", ram_out);
        
        ram_addr = 2'b01;
        #10;
        $display("RAM[1] = %h", ram_out);
        
        ram_addr = 2'b10;
        #10;
        $display("RAM[2] = %h", ram_out);
        
        ram_addr = 2'b11;
        #10;
        $display("RAM[3] = %h", ram_out);
        
        #10;
        $finish;
    end
endmodule

Sistemas Digitais 2/Aula 3/fpa_tb.vcd
$date
	Wed Apr  2 14:34:37 2025
$end
$version
	Icarus Verilog
$end
$timescale
	1s
$end
$scope module fpa_tb $end
$var wire 32 ! ram_out [31:0] $end
$var wire 1 " done $end
$var reg 2 # ram_addr [1:0] $end
$scope module dut $end
$var wire 2 $ ram_addr [1:0] $end
$var wire 32 % rom_out [31:0] $end
$var wire 32 & ram_out [31:0] $end
$var wire 2 ' ram_addr_mux [1:0] $end
$var wire 32 ( adder_sum [31:0] $end
$var parameter 4 ) COMPUTE_START $end
$var parameter 4 * COMPUTE_WAIT $end
$var parameter 4 + DONE_STATE $end
$var parameter 4 , IDLE $end
$var parameter 4 - READ_OP1_START $end
$var parameter 4 . READ_OP1_WAIT $end
$var parameter 4 / READ_OP2_START $end
$var parameter 4 0 READ_OP2_WAIT $end
$var parameter 4 1 WRITE_RAM $end
$var reg 1 2 adder_en $end
$var reg 2 3 addr_counter [1:0] $end
$var reg 1 4 clk $end
$var reg 1 " done $end
$var reg 32 5 operand_1 [31:0] $end
$var reg 32 6 operand_2 [31:0] $end
$var reg 1 7 ram_OE $end
$var reg 1 8 ram_RW $end
$var reg 1 9 rom_OE $end
$var reg 3 : rom_addr [2:0] $end
$var reg 4 ; state [3:0] $end
$scope module fp_adder $end
$var wire 1 4 clk $end
$var wire 1 2 en $end
$var wire 32 < operand_1 [31:0] $end
$var wire 32 = operand_2 [31:0] $end
$var wire 1 > sign_b $end
$var wire 1 ? sign_a $end
$var wire 23 @ frac_b [22:0] $end
$var wire 23 A frac_a [22:0] $end
$var wire 8 B exp_b [7:0] $end
$var wire 8 C exp_a [7:0] $end
$var reg 25 D aligned_smaller [24:0] $end
$var reg 8 E exp_larger [7:0] $end
$var reg 8 F exp_result [7:0] $end
$var reg 25 G frac_a_extended [24:0] $end
$var reg 25 H frac_b_extended [24:0] $end
$var reg 25 I frac_larger [24:0] $end
$var reg 23 J frac_result [22:0] $end
$var reg 25 K frac_smaller [24:0] $end
$var reg 8 L shift_amount [7:0] $end
$var reg 1 M sign_result $end
$var reg 32 N sum [31:0] $end
$var reg 25 O sum_fractions [24:0] $end
$upscope $end
$scope module ram_inst $end
$var wire 1 7 OE $end
$var wire 1 8 RW $end
$var wire 2 P addr [1:0] $end
$var wire 32 Q in [31:0] $end
$var reg 32 R out [31:0] $end
$upscope $end
$scope module rom_inst $end
$var wire 1 9 OE $end
$var wire 3 S addr [2:0] $end
$var reg 32 T out [31:0] $end
$upscope $end
$upscope $end
$upscope $end
$enddefinitions $end
$comment Show the parameter values. $end
$dumpall
b111 1
b100 0
b11 /
b10 .
b1 -
b0 ,
b1000 +
b110 *
b101 )
$end
#0
$dumpvars
bz T
b0 S
bz R
bz Q
b0 P
bx O
bz N
xM
bx L
bx K
bx J
bx I
bx H
bx G
bx F
bx E
bx D
b0 C
b0 B
b0 A
b0 @
0?
0>
b0 =
b0 <
b0 ;
b0 :
09
08
07
b0 6
b0 5
04
b0 3
02
bz (
b0 '
bz &
bz %
b0 $
b0 #
0"
bz !
$end
#5
b1001100001101010101101101000 %
b1001100001101010101101101000 T
b1 ;
19
14
#10
04
#15
b10 ;
14
#20
04
#25
b10011 C
b1101010101101101000 A
b11 ;
b1001100001101010101101101000 5
b1001100001101010101101101000 <
14
#30
04
#35
b10000001110000101101110101001 %
b10000001110000101101110101001 T
b100 ;
b1 :
b1 S
14
#40
04
#45
b100000 B
b1110000101101110101001 @
b101 ;
b10000001110000101101110101001 6
b10000001110000101101110101001 =
14
#50
04
#55
b110 ;
12
14
#60
04
#65
b111 ;
02
b10000110111000010111111101111 (
b10000110111000010111111101111 N
b10000110111000010111111101111 Q
b10111000010111111101111 J
b100001 F
0M
b1011100001011111110111100 O
b100001101010 D
b1101 L
b1000011010101011011010000 K
b1011100001011011101010010 I
b100000 E
b1011100001011011101010010 H
b1000011010101011011010000 G
14
#70
04
#75
b1 '
b1 P
b1 ;
b1 3
18
14
#80
04
#85
b111111100000000000000000000000 %
b111111100000000000000000000000 T
b10 ;
b10 :
b10 S
14
#90
04
#95
b1111111 C
b0 A
b11 ;
b111111100000000000000000000000 5
b111111100000000000000000000000 <
14
#100
04
#105
b111100010001001001101110100110 %
b111100010001001001101110100110 T
b100 ;
b11 :
b11 S
14
#110
04
#115
b1111000 B
b10001001001101110100110 @
b101 ;
b111100010001001001101110100110 6
b111100010001001001101110100110 =
14
#120
04
#125
b110 ;
12
14
#130
04
#135
b111 ;
02
b1000000010000001100010010011011 (
b1000000010000001100010010011011 N
b1000000010000001100010010011011 Q
b10000001100010010011011 J
b10000000 F
b1000000110001001001101110 O
b110001001001101110 D
b111 L
b1100010010011011101001100 K
b1000000000000000000000000 I
b1111111 E
b1100010010011011101001100 H
b1000000000000000000000000 G
14
#140
04
#145
b10 '
b10 P
b1 ;
b10 3
14
#150
04
#155
b1000000010000000000000000000000 %
b1000000010000000000000000000000 T
b10 ;
b100 :
b100 S
14
#160
04
#165
b10000000 C
b10000000000000000000000 A
b11 ;
b1000000010000000000000000000000 5
b1000000010000000000000000000000 <
14
#170
04
#175
b1000001001000000000000000000000 %
b1000001001000000000000000000000 T
b100 ;
b101 :
b101 S
14
#180
04
#185
b10000010 B
b1000000000000000000000 @
b101 ;
b1000001001000000000000000000000 6
b1000001001000000000000000000000 =
14
#190
04
#195
b110 ;
12
14
#200
04
#205
b111 ;
02
b1000001111010000000000000000000 (
b1000001111010000000000000000000 N
b1000001111010000000000000000000 Q
b11010000000000000000000 J
b10000011 F
b1101000000000000000000000 O
b11000000000000000000000 D
b10 L
b1100000000000000000000000 K
b1010000000000000000000000 I
b10000010 E
b1010000000000000000000000 H
b1100000000000000000000000 G
14
#210
04
#215
b11 '
b11 P
b1 ;
b11 3
14
#220
04
#225
b111110101000000000000000000000 %
b111110101000000000000000000000 T
b10 ;
b110 :
b110 S
14
#230
04
#235
b1111101 C
b1000000000000000000000 A
b11 ;
b111110101000000000000000000000 5
b111110101000000000000000000000 <
14
#240
04
#245
b111111011000000000000000000000 %
b111111011000000000000000000000 T
b100 ;
b111 :
b111 S
14
#250
04
#255
b1111110 B
b11000000000000000000000 @
b101 ;
b111111011000000000000000000000 6
b111111011000000000000000000000 =
14
#260
04
#265
b110 ;
12
14
#270
04
#275
b111 ;
02
b111111001100000000000000000000 (
b111111001100000000000000000000 N
b111111001100000000000000000000 Q
b1100000000000000000000 J
b1111110 F
b11000000000000000000000 O
b101000000000000000000000 D
b1 L
b1010000000000000000000000 K
b1110000000000000000000000 I
b1111110 E
b1110000000000000000000000 H
b1010000000000000000000000 G
14
#280
04
#285
b1000 ;
14
#290
04
#295
b0 '
b0 P
b10000110111000010111111101111 !
b10000110111000010111111101111 &
b10000110111000010111111101111 R
1"
17
08
14
#300
04
#305
14
#310
04
#315
b1000000010000001100010010011011 !
b1000000010000001100010010011011 &
b1000000010000001100010010011011 R
b1 '
b1 P
14
b1 #
b1 $
#320
04
#325
b1000001111010000000000000000000 !
b1000001111010000000000000000000 &
b1000001111010000000000000000000 R
b10 '
b10 P
14
b10 #
b10 $
#330
04
#335
b111111001100000000000000000000 !
b111111001100000000000000000000 &
b111111001100000000000000000000 R
b11 '
b11 P
14
b11 #
b11 $
